forcys/__init__.py
forcys/nc/__init__.py
forcys/nc/nc_datafile.py
forcys/nc/nc_variable.py
forcys/time_funcs.py
forcys/wavedata.py
forcys-0.1.3.dist-info/LICENSE
forcys-0.1.3.dist-info/METADATA
forcys-0.1.3.dist-info/WHEEL
forcys-0.1.3.dist-info/RECORD
